sockstream/__init__.py
sockstream/client_enhanced.py
sockstream/message_handler.py
sockstream/performance_handler.py
sockstream/protocol_handler.py
sockstream/security_handler.py
sockstream/server_enhanced.py
sockstream-1.0.2.dist-info/METADATA
sockstream-1.0.2.dist-info/WHEEL
sockstream-1.0.2.dist-info/top_level.txt
sockstream-1.0.2.dist-info/RECORD
