Metadata-Version: 2.1
Name: sockstream
Version: 1.0.2
Summary: A Python package for handling socket communications with advanced functionality
Home-page: https://github.com/ayammaximilian/sockstream
Author: Ayam Maximilian
Author-email: ayammaxmillian@gmail.com
Classifier: Development Status :: 4 - Beta
Classifier: Intended Audience :: Developers
Classifier: License :: OSI Approved :: MIT License
Classifier: Operating System :: OS Independent
Classifier: Programming Language :: Python :: 3
Classifier: Programming Language :: Python :: 3.7
Classifier: Programming Language :: Python :: 3.8
Classifier: Programming Language :: Python :: 3.9
Classifier: Programming Language :: Python :: 3.10
Classifier: Programming Language :: Python :: 3.11
Requires-Python: >=3.7
Requires-Dist: msgpack
Requires-Dist: protobuf
Requires-Dist: cryptography
Requires-Dist: bcrypt
Provides-Extra: all
Requires-Dist: uvloop; sys_platform != "win32" and extra == "all"
Provides-Extra: dev
Requires-Dist: pytest>=6.0; extra == "dev"
Requires-Dist: pytest-cov>=2.0; extra == "dev"
Requires-Dist: black>=21.0; extra == "dev"
Requires-Dist: flake8>=3.8; extra == "dev"
Provides-Extra: performance
Requires-Dist: uvloop; sys_platform != "win32" and extra == "performance"
